scrumit/__init__.py
scrumit/cmd.py
scrumit/config.py
scrumit/default_paraphraser_examples.json
scrumit/default_recognizer_examples.json
scrumit/entity/__init__.py
scrumit/entity/paraphraser.py
scrumit/entity/recognizer.py
scrumit/entity/scrumit.py
scrumit/paraphraser/__init__.py
scrumit/paraphraser/base.py
scrumit/paraphraser/exceptions.py
scrumit/paraphraser/backends/__init__.py
scrumit/paraphraser/backends/openai.py
scrumit/recognizer/__init__.py
scrumit/recognizer/base.py
scrumit/recognizer/exceptions.py
scrumit/recognizer/backends/__init__.py
scrumit/recognizer/backends/openai.py
scrumit/scrumer/__init__.py
scrumit/scrumer/base.py
scrumit/scrumer/exceptions.py
scrumit/scrumer/scrumit.py
scrumit-0.0.3.dist-info/LICENSE
scrumit-0.0.3.dist-info/METADATA
scrumit-0.0.3.dist-info/WHEEL
scrumit-0.0.3.dist-info/entry_points.txt
scrumit-0.0.3.dist-info/top_level.txt
scrumit-0.0.3.dist-info/RECORD
