Metadata-Version: 2.1
Name: scrumit
Version: 0.0.3
Summary: Package that converts raw text to scrum user stories
License: GNU GENERAL PUBLIC LICENSE
Classifier: Programming Language :: Python :: 3.10
Classifier: Operating System :: OS Independent
Classifier: License :: OSI Approved :: GNU General Public License v3 (GPLv3)
Requires-Python: >=3.10.9
License-File: LICENSE
Requires-Dist: aiohttp (==3.8.4)
Requires-Dist: aiosignal (==1.3.1)
Requires-Dist: appdirs (==1.4.4)
Requires-Dist: async-timeout (==4.0.2)
Requires-Dist: attrs (==23.1.0)
Requires-Dist: bleach (==6.0.0)
Requires-Dist: certifi (==2023.5.7)
Requires-Dist: charset-normalizer (==3.1.0)
Requires-Dist: click (==8.1.3)
Requires-Dist: colorama (==0.4.6)
Requires-Dist: docutils (==0.20.1)
Requires-Dist: et-xmlfile (==1.1.0)
Requires-Dist: exceptiongroup (==1.1.1)
Requires-Dist: frozenlist (==1.3.3)
Requires-Dist: idna (==3.4)
Requires-Dist: importlib-metadata (==6.7.0)
Requires-Dist: iniconfig (==2.0.0)
Requires-Dist: jaraco.classes (==3.2.3)
Requires-Dist: Jinja2 (==2.11.3)
Requires-Dist: keyring (==24.2.0)
Requires-Dist: markdown-it-py (==3.0.0)
Requires-Dist: MarkupSafe (==2.0.1)
Requires-Dist: mdurl (==0.1.2)
Requires-Dist: more-itertools (==9.1.0)
Requires-Dist: multidict (==6.0.4)
Requires-Dist: numpy (==1.25.0)
Requires-Dist: openai (==0.25.0)
Requires-Dist: openpyxl (==3.1.2)
Requires-Dist: packaging (==23.1)
Requires-Dist: pandas (==2.0.3)
Requires-Dist: pandas-stubs (==2.0.2.230605)
Requires-Dist: pkginfo (==1.9.6)
Requires-Dist: pluggy (==1.2.0)
Requires-Dist: promptify (==0.1.4)
Requires-Dist: pydantic (==1.10.9)
Requires-Dist: Pygments (==2.15.1)
Requires-Dist: pyproject-hooks (==1.0.0)
Requires-Dist: pytest (==7.4.0)
Requires-Dist: python-dateutil (==2.8.2)
Requires-Dist: python-dotenv (==1.0.0)
Requires-Dist: pytz (==2023.3)
Requires-Dist: readme-renderer (==40.0)
Requires-Dist: regex (==2022.10.31)
Requires-Dist: requests (==2.31.0)
Requires-Dist: requests-toolbelt (==1.0.0)
Requires-Dist: rfc3986 (==2.0.0)
Requires-Dist: rich (==13.4.2)
Requires-Dist: shellingham (==1.5.0.post1)
Requires-Dist: six (==1.16.0)
Requires-Dist: tomli (==2.0.1)
Requires-Dist: tqdm (==4.65.0)
Requires-Dist: typer (==0.9.0)
Requires-Dist: types-pytz (==2023.3.0.0)
Requires-Dist: typing-extensions (==4.7.0)
Requires-Dist: tzdata (==2023.3)
Requires-Dist: urllib3 (==2.0.3)
Requires-Dist: webencodings (==0.5.1)
Requires-Dist: yarl (==1.9.2)
Requires-Dist: zipp (==3.15.0)
